odoo/addons/account_payment_return_financial_risk/README.rst
odoo/addons/account_payment_return_financial_risk/__init__.py
odoo/addons/account_payment_return_financial_risk/__manifest__.py
odoo/addons/account_payment_return_financial_risk/i18n/account_payment_return_financial_risk.pot
odoo/addons/account_payment_return_financial_risk/i18n/am.po
odoo/addons/account_payment_return_financial_risk/i18n/ar.po
odoo/addons/account_payment_return_financial_risk/i18n/bg.po
odoo/addons/account_payment_return_financial_risk/i18n/bs.po
odoo/addons/account_payment_return_financial_risk/i18n/ca.po
odoo/addons/account_payment_return_financial_risk/i18n/cs.po
odoo/addons/account_payment_return_financial_risk/i18n/da.po
odoo/addons/account_payment_return_financial_risk/i18n/de.po
odoo/addons/account_payment_return_financial_risk/i18n/el_GR.po
odoo/addons/account_payment_return_financial_risk/i18n/en_GB.po
odoo/addons/account_payment_return_financial_risk/i18n/es.po
odoo/addons/account_payment_return_financial_risk/i18n/es_CR.po
odoo/addons/account_payment_return_financial_risk/i18n/es_EC.po
odoo/addons/account_payment_return_financial_risk/i18n/es_MX.po
odoo/addons/account_payment_return_financial_risk/i18n/es_VE.po
odoo/addons/account_payment_return_financial_risk/i18n/et.po
odoo/addons/account_payment_return_financial_risk/i18n/eu.po
odoo/addons/account_payment_return_financial_risk/i18n/fi.po
odoo/addons/account_payment_return_financial_risk/i18n/fr.po
odoo/addons/account_payment_return_financial_risk/i18n/fr_CA.po
odoo/addons/account_payment_return_financial_risk/i18n/fr_CH.po
odoo/addons/account_payment_return_financial_risk/i18n/gl.po
odoo/addons/account_payment_return_financial_risk/i18n/hr.po
odoo/addons/account_payment_return_financial_risk/i18n/hr_HR.po
odoo/addons/account_payment_return_financial_risk/i18n/hu.po
odoo/addons/account_payment_return_financial_risk/i18n/id.po
odoo/addons/account_payment_return_financial_risk/i18n/it.po
odoo14_addon_account_payment_return_financial_risk-14.0.1.0.1.dev5.dist-info/METADATA
odoo14_addon_account_payment_return_financial_risk-14.0.1.0.1.dev5.dist-info/WHEEL
odoo14_addon_account_payment_return_financial_risk-14.0.1.0.1.dev5.dist-info/top_level.txt
odoo14_addon_account_payment_return_financial_risk-14.0.1.0.1.dev5.dist-info/RECORD
